racer/__init__.py
racer/racer.py
task_racer-0.0.5.dist-info/LICENSE
task_racer-0.0.5.dist-info/METADATA
task_racer-0.0.5.dist-info/WHEEL
task_racer-0.0.5.dist-info/top_level.txt
task_racer-0.0.5.dist-info/RECORD
