Metadata-Version: 2.1
Name: task-racer
Version: 0.0.5
Summary: A Task Runner Framework
Home-page: https://github.com/bpradana/racer
Author: Bintang Pradana Erlangga Putra
Author-email: <work.bpradana@gmail.com>
License: MIT
Keywords: python,race condition,task,runner
Classifier: Development Status :: 1 - Planning
Classifier: Intended Audience :: Developers
Classifier: Programming Language :: Python :: 3
License-File: LICENSE
